emberfall/__init__.py
emberfall/ascii_art.py
emberfall/combat.py
emberfall/dungeon_generator.py
emberfall/fov.py
emberfall/game_map.py
emberfall/items.py
emberfall/main.py
emberfall/monster.py
emberfall/player.py
emberfall-0.1.0.dist-info/METADATA
emberfall-0.1.0.dist-info/WHEEL
emberfall-0.1.0.dist-info/entry_points.txt
emberfall-0.1.0.dist-info/top_level.txt
emberfall-0.1.0.dist-info/RECORD
