Metadata-Version: 2.4
Name: emberfall
Version: 0.1.0
Summary: A magical roguelike game - Chronicles of Emberfall
Home-page: https://github.com/nullsec0x/terminus-veil-chronicles-of-emberfall
Author: Nullsec0x
Author-email: contact@nullsec0x.dev
License: MIT
Keywords: roguelike,game,terminal,textual,ascii
Classifier: Development Status :: 4 - Beta
Classifier: Intended Audience :: End Users/Desktop
Classifier: License :: OSI Approved :: MIT License
Classifier: Operating System :: OS Independent
Classifier: Programming Language :: Python :: 3
Classifier: Programming Language :: Python :: 3.7
Classifier: Programming Language :: Python :: 3.8
Classifier: Programming Language :: Python :: 3.9
Classifier: Programming Language :: Python :: 3.10
Classifier: Programming Language :: Python :: 3.11
Requires-Python: >=3.7
Requires-Dist: textual>=0.1.18
Dynamic: author
Dynamic: author-email
Dynamic: classifier
Dynamic: description
Dynamic: description-content-type
Dynamic: home-page
Dynamic: keywords
Dynamic: license
Dynamic: requires-dist
Dynamic: requires-python
Dynamic: summary
